mx_edi/__init__.py
mx_edi/utils.py
mx_edi/connectors/__init__.py
mx_edi/connectors/sat/__init__.py
mx_edi/connectors/sat/certificate_handler.py
mx_edi/connectors/sat/enums.py
mx_edi/connectors/sat/envelope_signer.py
mx_edi/connectors/sat/package.py
mx_edi/connectors/sat/query.py
mx_edi/connectors/sat/sat_connector.py
mx_edi/connectors/sat/sat_login_handler.py
mx_edi/connectors/sat/utils.py
mx_edi/connectors/sat/package_parsers/__init__.py
mx_edi/connectors/sat/package_parsers/cfdi_parser.py
mx_edi/connectors/sat/package_parsers/metadata2cfdi.py
mx_edi/connectors/sat/package_parsers/utils.py
mx_edi/connectors/sat/package_parsers/xml2cfdi.py
mx_edi/connectors/sat/response_parsers/__init__.py
mx_edi/connectors/sat/response_parsers/download_response_parser.py
mx_edi/connectors/sat/response_parsers/login_response_parser.py
mx_edi/connectors/sat/response_parsers/query_response_parser.py
mx_edi/connectors/sat/response_parsers/response_parser.py
mx_edi/connectors/sat/response_parsers/verify_response_parser.py
mx_edi/connectors/sat/templates/__init__.py
mx_edi/connectors/sat/templates/common/Envelope.xml
mx_edi/connectors/sat/templates/common/KeyInfo.xml
mx_edi/connectors/sat/templates/common/Signature.xml
mx_edi/connectors/sat/templates/common/SignedInfo.xml
mx_edi/connectors/sat/templates/common/__init__.py
mx_edi/connectors/sat/templates/download/PeticionDescargaMasivaTercerosEntrada.xml
mx_edi/connectors/sat/templates/download/__init__.py
mx_edi/connectors/sat/templates/login/Envelope.xml
mx_edi/connectors/sat/templates/login/Timestamp.xml
mx_edi/connectors/sat/templates/login/__init__.py
mx_edi/connectors/sat/templates/query/SolicitaDescarga.xml
mx_edi/connectors/sat/templates/query/__init__.py
mx_edi/connectors/sat/templates/verify/VerificaSolicitudDescarga.xml
mx_edi/connectors/sat/templates/verify/__init__.py
mx_edi/core/__init__.py
mx_edi/core/cfdi.py
mx_edi/core/concepto.py
mx_edi/processors/__init__.py
mx_edi/processors/base.py
mx_edi/processors/efos.py
sat_ws-3.25.0.dist-info/LICENSE.md
sat_ws-3.25.0.dist-info/METADATA
sat_ws-3.25.0.dist-info/WHEEL
sat_ws-3.25.0.dist-info/top_level.txt
sat_ws-3.25.0.dist-info/RECORD
