Metadata-Version: 2.1
Name: sat-ws
Version: 3.25.0
Summary: API to connect with SAT ws
Home-page: https://gitlab.com/HomebrewSoft/sat_ws_api
Author: Moisés Navarro
Author-email: moisalejandro@gmail.com
Classifier: Programming Language :: Python :: 3
Classifier: Operating System :: OS Independent
Requires-Python: >=3.6
License-File: LICENSE.md
Requires-Dist: pyOpenSSL >=20.0.1
Requires-Dist: requests >=2.25.1
Requires-Dist: xmltodict >=0.12.0
